DeepPhysX.Sofa-22.12.1-py3.10-nspkg.pth
DeepPhysX/Sofa/__init__.py
DeepPhysX/Sofa/Environment/SofaEnvironment.py
DeepPhysX/Sofa/Environment/SofaEnvironmentConfig.py
DeepPhysX/Sofa/Environment/__init__.py
DeepPhysX/Sofa/Environment/launcherSofaEnvironment.py
DeepPhysX/Sofa/Pipeline/SofaPrediction.py
DeepPhysX/Sofa/Pipeline/__init__.py
DeepPhysX/examples/Sofa/demos/__init__.py
DeepPhysX/examples/Sofa/demos/Armadillo/__init__.py
DeepPhysX/examples/Sofa/demos/Armadillo/FC/__init__.py
DeepPhysX/examples/Sofa/demos/Armadillo/FC/dataset.py
DeepPhysX/examples/Sofa/demos/Armadillo/FC/download.py
DeepPhysX/examples/Sofa/demos/Armadillo/FC/prediction.py
DeepPhysX/examples/Sofa/demos/Armadillo/FC/runSofa.py
DeepPhysX/examples/Sofa/demos/Armadillo/FC/training.py
DeepPhysX/examples/Sofa/demos/Armadillo/FC/validation.py
DeepPhysX/examples/Sofa/demos/Armadillo/FC/Environment/ArmadilloPrediction.py
DeepPhysX/examples/Sofa/demos/Armadillo/FC/Environment/ArmadilloSofa.py
DeepPhysX/examples/Sofa/demos/Armadillo/FC/Environment/ArmadilloTraining.py
DeepPhysX/examples/Sofa/demos/Armadillo/FC/Environment/ArmadilloValidation.py
DeepPhysX/examples/Sofa/demos/Armadillo/FC/Environment/__init__.py
DeepPhysX/examples/Sofa/demos/Armadillo/FC/Environment/parameters.py
DeepPhysX/examples/Sofa/demos/Armadillo/FC/Environment/utils.py
DeepPhysX/examples/Sofa/demos/Armadillo/UNet/__init__.py
DeepPhysX/examples/Sofa/demos/Armadillo/UNet/dataset.py
DeepPhysX/examples/Sofa/demos/Armadillo/UNet/download.py
DeepPhysX/examples/Sofa/demos/Armadillo/UNet/prediction.py
DeepPhysX/examples/Sofa/demos/Armadillo/UNet/runSofa.py
DeepPhysX/examples/Sofa/demos/Armadillo/UNet/training.py
DeepPhysX/examples/Sofa/demos/Armadillo/UNet/validation.py
DeepPhysX/examples/Sofa/demos/Armadillo/UNet/Environment/ArmadilloPrediction.py
DeepPhysX/examples/Sofa/demos/Armadillo/UNet/Environment/ArmadilloSofa.py
DeepPhysX/examples/Sofa/demos/Armadillo/UNet/Environment/ArmadilloTraining.py
DeepPhysX.Sofa-22.12.1.dist-info/LICENSE
DeepPhysX.Sofa-22.12.1.dist-info/METADATA
DeepPhysX.Sofa-22.12.1.dist-info/WHEEL
DeepPhysX.Sofa-22.12.1.dist-info/namespace_packages.txt
DeepPhysX.Sofa-22.12.1.dist-info/top_level.txt
DeepPhysX.Sofa-22.12.1.dist-info/RECORD
