Metadata-Version: 2.1
Name: DeepPhysX.Sofa
Version: 22.12.1
Summary: A SOFA compatibility layer for DeepPhysX framework.
Home-page: https://github.com/mimesis-inria/DeepPhysX.Sofa
Author: Mimesis
Author-email: robin.enjalbert@inria.fr
License-File: LICENSE
Requires-Dist: DeepPhysX (>=22.12)
